openports/__init__.py
openports/cli.py
openports/script.py
openports-0.0.3.dist-info/licenses/LICENSE
openports-0.0.3.dist-info/METADATA
openports-0.0.3.dist-info/WHEEL
openports-0.0.3.dist-info/entry_points.txt
openports-0.0.3.dist-info/top_level.txt
openports-0.0.3.dist-info/RECORD
